pyenergydiagrams/__init__.py
pyenergydiagrams/_version.py
pyenergydiagrams/main.py
pyeergydiagrams-0.2.dist-info/LICENSE
pyeergydiagrams-0.2.dist-info/METADATA
pyeergydiagrams-0.2.dist-info/WHEEL
pyeergydiagrams-0.2.dist-info/top_level.txt
pyeergydiagrams-0.2.dist-info/RECORD
