Metadata-Version: 2.1
Name: pyeergydiagrams
Version: 0.2
Summary: Extract matplotlib plots components
Home-page: https://github.com/RemDelaporteMathurin/pyEnergyDiagrams
Author: Remi Delaporte-Mathurin
Author-email: rdelaportemathurin@gmail.com
License: Apache Software License
Project-URL: Source, https://github.com/RemDelaporteMathurin/pyEnergyDiagrams
Project-URL: Tracker, https://github.com/RemDelaporteMathurin/pyEnergyDiagrams/issues
Classifier: Natural Language :: English
Classifier: Topic :: Scientific/Engineering
Classifier: Programming Language :: Python :: 3
Classifier: Programming Language :: Python :: 3.6
Classifier: Programming Language :: Python :: 3.7
Classifier: Programming Language :: Python :: 3.8
Classifier: Programming Language :: Python :: 3.9
Classifier: License :: OSI Approved :: Apache Software License
Classifier: Operating System :: OS Independent
Requires-Python: >=3.6
License-File: LICENSE
Requires-Dist: matplotlib (>=3.2.2)
Provides-Extra: tests
Requires-Dist: pytest (>=5.4.3) ; extra == 'tests'
Requires-Dist: matplotlib (>=3.2.2) ; extra == 'tests'
